{
  "city": "Mangalore",
  "updated_utc": "2026-07-01T22:30:00Z",
  "source": "openaq",
  "n_stations": 1,
  "pollutants": {
    "pm10": {
      "value": 27.527152777777776,
      "unit": "µg/m³",
      "naqi_subindex": 27,
      "us_subindex": 25
    }
  },
  "aqi": {
    "naqi": {
      "index": null,
      "category": null,
      "dominant": [],
      "valid": false
    },
    "us": {
      "index": 25,
      "category": "Good",
      "dominant": [
        "pm10"
      ],
      "valid": true
    },
    "eu": {
      "band": "Fair",
      "category": "Fair",
      "dominant": [
        "pm10"
      ],
      "valid": true
    }
  },
  "weather": {
    "temp_c": 25.6,
    "rh_pct": 93,
    "precip_mm": 1.0,
    "wind_ms": 4.49,
    "wind_dir_deg": 258
  }
}